aea_ledger_fetchai/__init__.py
aea_ledger_fetchai/fetchai.py
aea_ledger_fetchai/hashfuncs.py
aea_ledger_fetchai/py.typed
aea_ledger_fetchai/test_tools/__init__.py
aea_ledger_fetchai/test_tools/constants.py
aea_ledger_fetchai/test_tools/docker_images.py
aea_ledger_fetchai/test_tools/fixture_helpers.py
aea_ledger_fetchai/test_tools/data/fetchai_private_key.txt
open_aea_ledger_fetchai-2.0.8.dist-info/licenses/LICENSE
open_aea_ledger_fetchai-2.0.8.dist-info/METADATA
open_aea_ledger_fetchai-2.0.8.dist-info/WHEEL
open_aea_ledger_fetchai-2.0.8.dist-info/entry_points.txt
open_aea_ledger_fetchai-2.0.8.dist-info/top_level.txt
open_aea_ledger_fetchai-2.0.8.dist-info/RECORD
